amstrax/__init__.py
amstrax/common.py
amstrax/contexts.py
amstrax/hitfinder_thresholds.py
amstrax/rundb.py
amstrax/auto_processing/__init__.py
amstrax/auto_processing/amstraxer.py
amstrax/auto_processing/amstraxer_easy.py
amstrax/auto_processing/auto_processing.py
amstrax/auto_processing/copy_live.py
amstrax/auto_processing/submit_stbc.py
amstrax/plugins/__init__.py
amstrax/plugins/events/__init__.py
amstrax/plugins/events/corrected_areas.py
amstrax/plugins/events/energy_estimates.py
amstrax/plugins/events/event_basics.py
amstrax/plugins/events/event_info.py
amstrax/plugins/events/event_positions.py
amstrax/plugins/events/events.py
amstrax/plugins/led_cal/__init__.py
amstrax/plugins/led_cal/led_calibration.py
amstrax/plugins/led_cal/records_led.py
amstrax/plugins/peaks/__init__.py
amstrax/plugins/peaks/peak_basics.py
amstrax/plugins/peaks/peak_classification.py
amstrax/plugins/peaks/peak_positions.py
amstrax/plugins/peaks/peaks.py
amstrax/plugins/raw_records/__init__.py
amstrax/plugins/raw_records/daqreader.py
amstrax/plugins/records/__init__.py
amstrax/plugins/records/pulse_processing.py
amstrax-2.2.0.data/scripts/process_run
amstrax-2.2.0.dist-info/METADATA
amstrax-2.2.0.dist-info/WHEEL
amstrax-2.2.0.dist-info/top_level.txt
amstrax-2.2.0.dist-info/RECORD
