Metadata-Version: 2.1
Name: amstrax
Version: 2.2.0
Summary: strax for XAMS data
Home-page: https://github.com/XAMS-nikhef/amstrax
Author: Nikhef
License: UNKNOWN
Platform: UNKNOWN
Classifier: Development Status :: 4 - Beta
Classifier: License :: OSI Approved :: BSD License
Classifier: Natural Language :: English
Classifier: Programming Language :: Python :: 3.8
Classifier: Programming Language :: Python :: 3.9
Classifier: Programming Language :: Python :: 3.10
Classifier: Intended Audience :: Science/Research
Classifier: Programming Language :: Python :: Implementation :: CPython
Classifier: Topic :: Scientific/Engineering :: Physics
Requires-Python: >=3.6
Requires-Dist: numpy
Requires-Dist: numba >=0.50.0
Requires-Dist: strax >=0.12.0
Requires-Dist: pymongo <4.0
Requires-Dist: IPython
Requires-Dist: sshtunnel
Requires-Dist: iminuit
Requires-Dist: matplotlib
Requires-Dist: packaging
Requires-Dist: gitpython
Provides-Extra: docs
Requires-Dist: numpy ==1.23.3 ; extra == 'docs'
Requires-Dist: autodocsumm ==0.2.9 ; extra == 'docs'
Requires-Dist: scipy ==1.9.1 ; extra == 'docs'
Requires-Dist: commonmark ==0.9.1 ; extra == 'docs'
Requires-Dist: gitpython ==3.1.30 ; extra == 'docs'
Requires-Dist: graphviz ==0.20.1 ; extra == 'docs'
Requires-Dist: nbsphinx ==0.8.9 ; extra == 'docs'
Requires-Dist: recommonmark ==0.7.1 ; extra == 'docs'
Requires-Dist: sphinx ==5.2.3 ; extra == 'docs'
Requires-Dist: sphinx-rtd-theme ==1.0.0 ; extra == 'docs'
Requires-Dist: sphinxcontrib-applehelp ==1.0.2 ; extra == 'docs'
Requires-Dist: sphinxcontrib-devhelp ==1.0.2 ; extra == 'docs'
Requires-Dist: sphinxcontrib-htmlhelp ==2.0.0 ; extra == 'docs'
Requires-Dist: sphinxcontrib-jsmath ==1.0.1 ; extra == 'docs'
Requires-Dist: sphinxcontrib-qthelp ==1.0.3 ; extra == 'docs'
Requires-Dist: typing-extensions ==4.3.0 ; extra == 'docs'
